fincura/__init__.py
fincura/api_client.py
fincura/api_wrapper.py
fincura/configuration.py
fincura/exceptions.py
fincura/model_utils.py
fincura/rest.py
fincura/api/__init__.py
fincura/api/api_key_api.py
fincura/api/borrowers_api.py
fincura/api/custom_attributes_api.py
fincura/api/data_views_api.py
fincura/api/embedded_workflows_api.py
fincura/api/files_api.py
fincura/api/loans_api.py
fincura/api/portfolios_api.py
fincura/api/requirements_api.py
fincura/api/tenant_settings_api.py
fincura/api/webhooks_api.py
fincura/apis/__init__.py
fincura/model/__init__.py
fincura/model/api_key.py
fincura/model/borrower.py
fincura/model/bulk_file_create.py
fincura/model/bulk_file_read.py
fincura/model/custom_attribute_definition.py
fincura/model/data_view.py
fincura/model/data_view_calculated_value.py
fincura/model/data_view_calculated_value_line_item.py
fincura/model/data_view_cell_format.py
fincura/model/data_view_cells.py
fincura/model/data_view_columns.py
fincura/model/data_view_row_format.py
fincura/model/data_view_rows.py
fincura/model/document_file_create.py
fincura/model/document_file_create_statements.py
fincura/model/document_file_read.py
fincura/model/embedded_workflow.py
fincura/model/embedded_workflow_ui_controls.py
fincura/model/financial_requirement.py
fincura/model/financial_requirement_rules.py
fincura/model/inline_response200.py
fincura/model/inline_response2001.py
fincura/model/inline_response2002.py
fincura/model/inline_response2003.py
fincura/model/inline_response2004.py
fincura/model/inline_response2005.py
fincura/model/inline_response2006.py
fincura/model/loan.py
fincura/model/loan_borrower_info.py
fincura/model/loan_compliance_info.py
fincura/model/loan_documents.py
fincura/model/loan_financials.py
fincura/model/loan_financials_calculated_value.py
fincura/model/loan_financials_cells.py
fincura/model/loan_financials_data_columns.py
fincura/model/loan_financials_template_items.py
fincura/model/loan_guarantors.py
fincura/model/loan_periods.py
fincura_api_client-1.0.2.dist-info/AUTHORS.md
fincura_api_client-1.0.2.dist-info/METADATA
fincura_api_client-1.0.2.dist-info/WHEEL
fincura_api_client-1.0.2.dist-info/top_level.txt
fincura_api_client-1.0.2.dist-info/RECORD
