Metadata-Version: 2.1
Name: fincura-api-client
Version: 1.0.2
Summary: Fincura API
Home-page: http://yada
Author: Fincura Engineering
Author-email: support@fincura.com
License: UNKNOWN
Keywords: OpenAPI,OpenAPI-Generator,Fincura API
Platform: UNKNOWN
Requires-Python: >=3.5
Requires-Dist: urllib3 (>=1.15)
Requires-Dist: certifi
Requires-Dist: python-dateutil
Requires-Dist: nulltype
